README.md
license.txt
setup.py
PIMSILITOOL.egg-info/PKG-INFO
PIMSILITOOL.egg-info/SOURCES.txt
PIMSILITOOL.egg-info/dependency_links.txt
PIMSILITOOL.egg-info/not-zip-safe
PIMSILITOOL.egg-info/top_level.txt
pimsilitool/__init__.py
pimsilitool/config.py
pimsilitool/pimsilitool.py
pimsilitool/anomalycomparer/__init__.py
pimsilitool/anomalycomparer/anomalycomparer.py
pimsilitool/anomalyconverter/__init__.py
pimsilitool/anomalyconverter/anomalyconverter.py
pimsilitool/anomalygrowthcalculator/__init__.py
pimsilitool/anomalygrowthcalculator/anomalygrowthcalculator.py
pimsilitool/anomalyprioritizer/__init__.py
pimsilitool/anomalyprioritizer/anomalyprioritizer.py
pimsilitool/anomalyprioritizer/anomalyprioritizer_bkp.py
pimsilitool/digsheetlayout/__init__.py
pimsilitool/digsheetlayout/digsheetlayout.py
pimsilitool/digsheetlayout/load_digsheet_data.py
pimsilitool/esri/__init__.py
pimsilitool/esri/toolboxes/PIMS ILI Data Integration.AnomalyComparer.pyt.xml
pimsilitool/esri/toolboxes/PIMS ILI Data Integration.AnomalyConverter.pyt.xml
pimsilitool/esri/toolboxes/PIMS ILI Data Integration.AnomalyGrowthCalculator.pyt.xml
pimsilitool/esri/toolboxes/PIMS ILI Data Integration.AnomalyPrioritizer.pyt.xml
pimsilitool/esri/toolboxes/PIMS ILI Data Integration.DigSheetLayout.pyt.xml
pimsilitool/esri/toolboxes/PIMS ILI Data Integration.PressureCalculator.pyt.xml
pimsilitool/esri/toolboxes/PIMS ILI Data Integration.RegisterLicense.pyt.xml
pimsilitool/esri/toolboxes/PIMS ILI Data Integration.RequestLicense.pyt.xml
pimsilitool/esri/toolboxes/PIMS ILI Data Integration.pyt
pimsilitool/esri/toolboxes/PIMS ILI Data Integration.pyt.xml
pimsilitool/esri/toolboxes/__init__.py
pimsilitool/esri/toolboxes/inlineinspection - Copy.pyt
pimsilitool/esri/toolboxes/inlineinspection - Copy.pyt.xml
pimsilitool/esri/toolboxes/inlineinspection.AnomalyComparer.pyt.xml
pimsilitool/esri/toolboxes/inlineinspection.AnomalyConverter.pyt.xml
pimsilitool/esri/toolboxes/inlineinspection.AnomalyGrowthCalculator.pyt.xml
pimsilitool/esri/toolboxes/inlineinspection.AnomalyPrioritizer.pyt.xml
pimsilitool/esri/toolboxes/inlineinspection.DigSheetLayout.pyt.xml
