Metadata-Version: 2.1
Name: PIMSILITOOL
Version: 0.0.14
Summary: Provides tools for PIMS ILI analysis
Home-page: http://g2-is.com
Author: G2 Integrated Solutions.
Author-email: support@g2-is.com
Maintainer: G2 Integrated Solutions
Maintainer-email: support@g2-is.com
License: license.txt
Project-URL: Documentation, https://knowledgecenter.g2-is.com/products/inlineinspection-tool/
Project-URL: Code, https://github.com/G2IntegratedSolutions/inlineinspection/
Project-URL: Issue tracker, https://github.com/G2IntegratedSolutions/inlineinspection/
Platform: UNKNOWN
Classifier: Programming Language :: Python :: 3
Classifier: Operating System :: Microsoft :: Windows
Requires-Python: >=3.6
License-File: license.txt
